ystafdb/__init__.py
ystafdb/config_parser.py
ystafdb/filesystem.py
ystafdb/foaf.py
ystafdb/graph_common.py
ystafdb/provenance_uris.py
ystafdb/ystafdb_metadata.py
ystafdb/bin/__init__.py
ystafdb/bin/ystafdb.py
ystafdb/data/__init__.py
ystafdb/data/config.json
ystafdb-0.6.0.dist-info/LICENSE
ystafdb-0.6.0.dist-info/METADATA
ystafdb-0.6.0.dist-info/WHEEL
ystafdb-0.6.0.dist-info/entry_points.txt
ystafdb-0.6.0.dist-info/top_level.txt
ystafdb-0.6.0.dist-info/RECORD
