Metadata-Version: 2.1
Name: ystafdb
Version: 0.6.0
Summary: CLI tool to parse YSTAFDB and produce ttl/nt/xml.
Home-page: https://github.com/BONSAMURAIS/ystafdb/
Author: Emil Riis Hansen
Author-email: emilrh@cs.aau.dk
License: UNKNOWN
Platform: UNKNOWN
Classifier: Intended Audience :: End Users/Desktop
Classifier: Intended Audience :: Developers
Classifier: Intended Audience :: Science/Research
Classifier: License :: OSI Approved :: BSD License
Classifier: Operating System :: MacOS :: MacOS X
Classifier: Operating System :: Microsoft :: Windows
Classifier: Operating System :: POSIX
Classifier: Programming Language :: Python
Classifier: Programming Language :: Python :: 3
Classifier: Programming Language :: Python :: 3.5
Classifier: Programming Language :: Python :: 3.6
Classifier: Programming Language :: Python :: 3.7
Classifier: Programming Language :: Python :: 3.8
Classifier: Topic :: Scientific/Engineering :: Information Analysis
Classifier: Topic :: Scientific/Engineering :: Mathematics
Classifier: Topic :: Scientific/Engineering :: Visualization
License-File: LICENSE
Requires-Dist: appdirs
Requires-Dist: docopt
Requires-Dist: rdflib (>=6)
Requires-Dist: pandas
Requires-Dist: xlrd
Requires-Dist: pyxlsb
